odoo/addons/stock_putaway_method/README.rst
odoo/addons/stock_putaway_method/__init__.py
odoo/addons/stock_putaway_method/__manifest__.py
odoo/addons/stock_putaway_method/i18n/cs_CZ.po
odoo/addons/stock_putaway_method/i18n/fr.po
odoo/addons/stock_putaway_method/i18n/stock_putaway_method.pot
odoo/addons/stock_putaway_method/models/__init__.py
odoo/addons/stock_putaway_method/models/product_strategy.py
odoo/addons/stock_putaway_method/static/description/icon.png
odoo/addons/stock_putaway_method/tests/__init__.py
odoo/addons/stock_putaway_method/tests/test_putaway_method.py
odoo/addons/stock_putaway_method/views/product_strategy_views.xml
odoo11_addon_stock_putaway_method-11.0.1.0.1.dist-info/METADATA
odoo11_addon_stock_putaway_method-11.0.1.0.1.dist-info/WHEEL
odoo11_addon_stock_putaway_method-11.0.1.0.1.dist-info/top_level.txt
odoo11_addon_stock_putaway_method-11.0.1.0.1.dist-info/RECORD
